hustmirror_cli-1.1.4.data/scripts/hustmirror-cli
hustmirror_cli-1.1.4.dist-info/METADATA
hustmirror_cli-1.1.4.dist-info/WHEEL
hustmirror_cli-1.1.4.dist-info/licenses/LICENSE
hustmirror_cli/__init__.py
hustmirror_cli-1.1.4.dist-info/RECORD
