Metadata-Version: 2.1
Name: hustmirror-cli
Version: 1.1.4
Summary: hustmirror-cli, hosted at PyPI
Author-Email: jingfelix <jingfelix@outlook.com>
License: MIT
Requires-Python: >=3.8
